sum_04670/__init__.py
sum_04670-0.0.1.dist-info/METADATA
sum_04670-0.0.1.dist-info/WHEEL
sum_04670-0.0.1.dist-info/license.txt
sum_04670-0.0.1.dist-info/top_level.txt
sum_04670-0.0.1.dist-info/RECORD
