Metadata-Version: 2.1
Name: sum-04670
Version: 0.0.1
Summary: adding number
Home-page: UNKNOWN
Author: sum_04670
Author-email: hizbullah.kandhro@gmail.com
License: UNKNOWN
Platform: UNKNOWN
Classifier: Programming Language :: Python :: 3
Classifier: License :: OSI Approved :: MIT License
Classifier: Operating System :: OS Independent
